simple_json_server/__init__.py
simple_json_server/simple_json_server.py
simple_json_server/public/admin.css
simple_json_server/public/admin.html
simple_json_server/public/admin.js
simple_json_server-0.2.0.dist-info/licenses/LICENSE
simple_json_server-0.2.0.dist-info/METADATA
simple_json_server-0.2.0.dist-info/WHEEL
simple_json_server-0.2.0.dist-info/entry_points.txt
simple_json_server-0.2.0.dist-info/top_level.txt
simple_json_server-0.2.0.dist-info/RECORD
