Metadata-Version: 2.4
Name: simple-json-server
Version: 0.2.0
Summary: A zero-dependency, lightweight REST API server based on a simple JSON file.
Author-email: 10mohi6 <10.mohi.6.y@gmail.com>
License: MIT License
Project-URL: Homepage, https://github.com/10mohi6/simple-json-server
Project-URL: Bug Tracker, https://github.com/10mohi6/simple-json-server/issues
Keywords: json-server,mock,api,rest,http-server,prototype
Classifier: Development Status :: 4 - Beta
Classifier: Intended Audience :: Developers
Classifier: License :: OSI Approved :: MIT License
Classifier: Programming Language :: Python :: 3
Classifier: Programming Language :: Python :: 3.9
Classifier: Programming Language :: Python :: 3.10
Classifier: Programming Language :: Python :: 3.11
Classifier: Programming Language :: Python :: 3.12
Classifier: Topic :: Internet :: WWW/HTTP :: HTTP Servers
Classifier: Topic :: Software Development :: Testing :: Mocking
Requires-Python: >=3.9
License-File: LICENSE
Provides-Extra: dev
Requires-Dist: pytest>=8.4.1; extra == "dev"
Requires-Dist: requests>=2.32.3; extra == "dev"
Requires-Dist: build>=1.2.1; extra == "dev"
Requires-Dist: twine>=5.1.1; extra == "dev"
Requires-Dist: pytest-cov>=5.0.0; extra == "dev"
Dynamic: license-file
